duckdbt/api.py
duckdbt/common.py
duckdbt/driver.py
duckdbt/extensions.py
duckdbt/ipython.py
duckdbt/load_db_profile.py
duckdbt/server.py
duckdbt/static/dashboard.css
duckdbt/static/favicon.ico
duckdbt/templates/index.html
duckdbt-0.5.1.dist-info/METADATA
duckdbt-0.5.1.dist-info/WHEEL
duckdbt-0.5.1.dist-info/top_level.txt
duckdbt-0.5.1.dist-info/RECORD
